nats_contrib/request_many/__about__.py
nats_contrib/request_many/__init__.py
nats_contrib/request_many/client.py
nats_contrib/request_many/executor.py
nats_contrib/request_many/iterator.py
nats_contrib/request_many/py.typed
nats_contrib/request_many/utils.py
nats_request_many-0.0.2.dist-info/LICENSE
nats_request_many-0.0.2.dist-info/METADATA
nats_request_many-0.0.2.dist-info/WHEEL
nats_request_many-0.0.2.dist-info/top_level.txt
nats_request_many-0.0.2.dist-info/RECORD
